wokki_chat_sdk-1.0.2.dist-info/licenses/LICENSE
wokkichat/__init__.py
wokkichat/enums.py
wokkichat/main.py
wokkichat/types.py
wokkichat/addons/__init__.py
wokkichat/addons/color.py
wokkichat/addons/ui.py
wokki_chat_sdk-1.0.2.dist-info/METADATA
wokki_chat_sdk-1.0.2.dist-info/WHEEL
wokki_chat_sdk-1.0.2.dist-info/top_level.txt
wokki_chat_sdk-1.0.2.dist-info/RECORD
