Metadata-Version: 2.4
Name: wokki-chat-sdk
Version: 1.0.2
Summary: Python SDK to make bots for Wokki Chat
Home-page: https://github.com/levkris/Wokki-Chat-Python-SDK
Author: Bjarnos & wokki20
License: Apache-2.0
Classifier: Programming Language :: Python :: 3
Classifier: Development Status :: 4 - Beta
Classifier: Natural Language :: English
Classifier: Topic :: Communications :: Chat
Classifier: Topic :: Software Development :: Libraries :: Python Modules
Classifier: Intended Audience :: Developers
Classifier: Environment :: Web Environment
Classifier: Framework :: AsyncIO
Classifier: Operating System :: OS Independent
Classifier: Typing :: Typed
Classifier: License :: OSI Approved :: Apache Software License
Requires-Python: >=3.6
License-File: LICENSE
Requires-Dist: python-socketio[client]
Requires-Dist: aiohttp
Dynamic: author
Dynamic: classifier
Dynamic: description
Dynamic: description-content-type
Dynamic: home-page
Dynamic: license
Dynamic: license-file
Dynamic: requires-dist
Dynamic: requires-python
Dynamic: summary
